{
  "v": "4.8.0",
  "meta": { "g": "LottieFiles AE 3.5.7", "a": "", "k": "", "d": "", "tc": "" },
  "fr": 25,
  "ip": 0,
  "op": 50,
  "w": 500,
  "h": 500,
  "nm": "13-Temperature",
  "ddd": 0,
  "assets": [],
  "layers": [
    {
      "ddd": 0,
      "ind": 1,
      "ty": 3,
      "nm": "Main Stroke width - Color Ctrl",
      "parent": 8,
      "sr": 1,
      "ks": {
        "o": { "a": 0, "k": 0, "ix": 11 },
        "r": { "a": 0, "k": 0, "ix": 10 },
        "p": { "a": 0, "k": [0, 0, 0], "ix": 2 },
        "a": { "a": 0, "k": [50, 50, 0], "ix": 1 },
        "s": { "a": 0, "k": [100, 100, 100], "ix": 6 }
      },
      "ao": 0,
      "ef": [
        {
          "ty": 5,
          "nm": "Stroke width",
          "np": 3,
          "mn": "ADBE Slider Control",
          "ix": 1,
          "en": 1,
          "ef": [
            {
              "ty": 0,
              "nm": "Slider",
              "mn": "ADBE Slider Control-0001",
              "ix": 1,
              "v": { "a": 0, "k": 16, "ix": 1 }
            }
          ]
        },
        {
          "ty": 5,
          "nm": "Highlight",
          "np": 3,
          "mn": "ADBE Color Control",
          "ix": 2,
          "en": 1,
          "ef": [
            {
              "ty": 2,
              "nm": "Color",
              "mn": "ADBE Color Control-0001",
              "ix": 1,
              "v": {
                "a": 0,
                "k": [0.992156863213, 0.376470595598, 0.313725501299, 1],
                "ix": 1
              }
            }
          ]
        },
        {
          "ty": 5,
          "nm": "Base color",
          "np": 3,
          "mn": "ADBE Color Control",
          "ix": 3,
          "en": 1,
          "ef": [
            {
              "ty": 2,
              "nm": "Color",
              "mn": "ADBE Color Control-0001",
              "ix": 1,
              "v": {
                "a": 0,
                "k": [0.019607843831, 0.164705887437, 0.458823531866, 1],
                "ix": 1
              }
            }
          ]
        }
      ],
      "ip": 0,
      "op": 50,
      "st": 0,
      "bm": 0
    },
    {
      "ddd": 0,
      "ind": 2,
      "ty": 4,
      "nm": "lines 2",
      "parent": 4,
      "sr": 1,
      "ks": {
        "o": { "a": 0, "k": 100, "ix": 11 },
        "r": { "a": 0, "k": -110.955, "ix": 10 },
        "p": { "a": 0, "k": [157.146, -31.056, 0], "ix": 2 },
        "a": { "a": 0, "k": [111.215, -110.795, 0], "ix": 1 },
        "s": { "a": 0, "k": [100, 100, 100], "ix": 6 }
      },
      "ao": 0,
      "shapes": [
        {
          "ty": "gr",
          "it": [
            {
              "ind": 0,
              "ty": "sh",
              "ix": 1,
              "ks": {
                "a": 0,
                "k": {
                  "i": [[0, 0], [0, 0]],
                  "o": [[0, 0], [0, 0]],
                  "v": [[111.215, -110.795], [-25.881, -115.788]],
                  "c": false
                },
                "ix": 2
              },
              "nm": "Path 1",
              "mn": "ADBE Vector Shape - Group",
              "hd": false
            },
            {
              "ty": "st",
              "c": {
                "a": 0,
                "k": [0.2, 0.8, 0.8, 1],
                "ix": 3,
                "x": "var $bm_rt;\n$bm_rt = thisComp.layer('Main Stroke width - Color Ctrl').effect('Highlight')('Color');"
              },
              "o": { "a": 0, "k": 100, "ix": 4 },
              "w": {
                "a": 0,
                "k": 16,
                "ix": 5,
                "x": "var $bm_rt;\n$bm_rt = thisComp.layer('Main Stroke width - Color Ctrl').effect('Stroke width')('Slider');"
              },
              "lc": 2,
              "lj": 1,
              "ml": 4,
              "bm": 0,
              "nm": "Stroke 1",
              "mn": "ADBE Vector Graphic - Stroke",
              "hd": false
            },
            {
              "ty": "tr",
              "p": { "a": 0, "k": [0, 0], "ix": 2 },
              "a": { "a": 0, "k": [0, 0], "ix": 1 },
              "s": { "a": 0, "k": [100, 100], "ix": 3 },
              "r": { "a": 0, "k": 0, "ix": 6 },
              "o": { "a": 0, "k": 100, "ix": 7 },
              "sk": { "a": 0, "k": 0, "ix": 4 },
              "sa": { "a": 0, "k": 0, "ix": 5 },
              "nm": "Transform"
            }
          ],
          "nm": "Shape 1",
          "np": 3,
          "cix": 2,
          "bm": 0,
          "ix": 1,
          "mn": "ADBE Vector Group",
          "hd": false
        },
        {
          "ty": "tm",
          "s": {
            "a": 1,
            "k": [
              {
                "i": { "x": [0.59], "y": [1] },
                "o": { "x": [0.41], "y": [0] },
                "t": 19.5,
                "s": [0]
              },
              { "t": 26, "s": [100] }
            ],
            "ix": 1
          },
          "e": {
            "a": 1,
            "k": [
              {
                "i": { "x": [0.59], "y": [1] },
                "o": { "x": [0.41], "y": [0] },
                "t": 13,
                "s": [0]
              },
              { "t": 21.357421875, "s": [100] }
            ],
            "ix": 2
          },
          "o": { "a": 0, "k": 0, "ix": 3 },
          "m": 1,
          "ix": 2,
          "nm": "Trim Paths 1",
          "mn": "ADBE Vector Filter - Trim",
          "hd": false
        }
      ],
      "ip": -5,
      "op": 45,
      "st": -5,
      "bm": 0
    },
    {
      "ddd": 0,
      "ind": 3,
      "ty": 4,
      "nm": "lines",
      "parent": 4,
      "sr": 1,
      "ks": {
        "o": { "a": 0, "k": 100, "ix": 11 },
        "r": { "a": 0, "k": 0, "ix": 10 },
        "p": { "a": 0, "k": [-127.307, -187.569, 0], "ix": 2 },
        "a": { "a": 0, "k": [-29, -169, 0], "ix": 1 },
        "s": { "a": 0, "k": [100, 100, 100], "ix": 6 }
      },
      "ao": 0,
      "shapes": [
        {
          "ty": "gr",
          "it": [
            {
              "ind": 0,
              "ty": "sh",
              "ix": 1,
              "ks": {
                "a": 0,
                "k": {
                  "i": [[0, 0], [0, 0]],
                  "o": [[0, 0], [0, 0]],
                  "v": [[111.215, -110.795], [-25.881, -115.788]],
                  "c": false
                },
                "ix": 2
              },
              "nm": "Path 1",
              "mn": "ADBE Vector Shape - Group",
              "hd": false
            },
            {
              "ty": "st",
              "c": {
                "a": 0,
                "k": [0.2, 0.8, 0.8, 1],
                "ix": 3,
                "x": "var $bm_rt;\n$bm_rt = thisComp.layer('Main Stroke width - Color Ctrl').effect('Highlight')('Color');"
              },
              "o": { "a": 0, "k": 100, "ix": 4 },
              "w": {
                "a": 0,
                "k": 16,
                "ix": 5,
                "x": "var $bm_rt;\n$bm_rt = thisComp.layer('Main Stroke width - Color Ctrl').effect('Stroke width')('Slider');"
              },
              "lc": 2,
              "lj": 1,
              "ml": 4,
              "bm": 0,
              "nm": "Stroke 1",
              "mn": "ADBE Vector Graphic - Stroke",
              "hd": false
            },
            {
              "ty": "tr",
              "p": { "a": 0, "k": [0, 0], "ix": 2 },
              "a": { "a": 0, "k": [0, 0], "ix": 1 },
              "s": { "a": 0, "k": [100, 100], "ix": 3 },
              "r": { "a": 0, "k": 0, "ix": 6 },
              "o": { "a": 0, "k": 100, "ix": 7 },
              "sk": { "a": 0, "k": 0, "ix": 4 },
              "sa": { "a": 0, "k": 0, "ix": 5 },
              "nm": "Transform"
            }
          ],
          "nm": "Shape 1",
          "np": 3,
          "cix": 2,
          "bm": 0,
          "ix": 1,
          "mn": "ADBE Vector Group",
          "hd": false
        },
        {
          "ty": "tm",
          "s": {
            "a": 1,
            "k": [
              {
                "i": { "x": [0.59], "y": [1] },
                "o": { "x": [0.41], "y": [0] },
                "t": 19.5,
                "s": [0]
              },
              { "t": 26, "s": [100] }
            ],
            "ix": 1
          },
          "e": {
            "a": 1,
            "k": [
              {
                "i": { "x": [0.59], "y": [1] },
                "o": { "x": [0.41], "y": [0] },
                "t": 13,
                "s": [0]
              },
              { "t": 21.357421875, "s": [100] }
            ],
            "ix": 2
          },
          "o": { "a": 0, "k": 0, "ix": 3 },
          "m": 1,
          "ix": 2,
          "nm": "Trim Paths 1",
          "mn": "ADBE Vector Filter - Trim",
          "hd": false
        }
      ],
      "ip": -5,
      "op": 45,
      "st": -5,
      "bm": 0
    },
    {
      "ddd": 0,
      "ind": 4,
      "ty": 4,
      "nm": "Termometer",
      "parent": 1,
      "sr": 1,
      "ks": {
        "o": { "a": 0, "k": 100, "ix": 11 },
        "r": {
          "a": 1,
          "k": [
            {
              "i": { "x": [0.53], "y": [1] },
              "o": { "x": [0.47], "y": [0] },
              "t": 0,
              "s": [0]
            },
            {
              "i": { "x": [0.53], "y": [1] },
              "o": { "x": [0.47], "y": [0] },
              "t": 10,
              "s": [-25.452]
            },
            {
              "i": { "x": [0.53], "y": [1] },
              "o": { "x": [0.47], "y": [0] },
              "t": 17,
              "s": [10]
            },
            {
              "i": { "x": [0.53], "y": [1] },
              "o": { "x": [0.47], "y": [0] },
              "t": 24,
              "s": [-5]
            },
            {
              "i": { "x": [0.833], "y": [1] },
              "o": { "x": [0.167], "y": [0] },
              "t": 33,
              "s": [2]
            },
            { "t": 38, "s": [0] }
          ],
          "ix": 10
        },
        "p": { "a": 0, "k": [51.141, 48.859, 0], "ix": 2 },
        "a": { "a": 0, "k": [1.141, -1.141, 0], "ix": 1 },
        "s": { "a": 0, "k": [100, 100, 100], "ix": 6 }
      },
      "ao": 0,
      "shapes": [
        {
          "ty": "gr",
          "it": [
            {
              "ind": 0,
              "ty": "sh",
              "ix": 1,
              "ks": {
                "a": 0,
                "k": {
                  "i": [
                    [1.359, 24.554],
                    [0, 0],
                    [23.32, 23.32],
                    [0, 0],
                    [23.32, -23.32],
                    [0, 0],
                    [18.757, -18.757],
                    [-34.98, -34.98],
                    [-34.98, 34.98]
                  ],
                  "o": [
                    [0, 0],
                    [23.32, -23.32],
                    [0, 0],
                    [-23.32, -23.32],
                    [0, 0],
                    [-24.554, -1.359],
                    [-34.98, 34.98],
                    [34.98, 34.98],
                    [18.757, -18.757]
                  ],
                  "v": [
                    [-10.972, 95.421],
                    [174.766, -90.316],
                    [174.766, -174.766],
                    [174.766, -174.766],
                    [90.316, -174.766],
                    [-95.422, 10.972],
                    [-163.738, 37.064],
                    [-163.738, 163.738],
                    [-37.064, 163.738]
                  ],
                  "c": true
                },
                "ix": 2
              },
              "nm": "Path 1",
              "mn": "ADBE Vector Shape - Group",
              "hd": false
            },
            {
              "ty": "st",
              "c": {
                "a": 0,
                "k": [0, 0, 0, 1],
                "ix": 3,
                "x": "var $bm_rt;\n$bm_rt = thisComp.layer('Main Stroke width - Color Ctrl').effect('Base color')('Color');"
              },
              "o": { "a": 0, "k": 100, "ix": 4 },
              "w": {
                "a": 0,
                "k": 16,
                "ix": 5,
                "x": "var $bm_rt;\n$bm_rt = thisComp.layer('Main Stroke width - Color Ctrl').effect('Stroke width')('Slider');"
              },
              "lc": 2,
              "lj": 2,
              "bm": 0,
              "nm": "Stroke 1",
              "mn": "ADBE Vector Graphic - Stroke",
              "hd": false
            },
            {
              "ty": "tr",
              "p": { "a": 0, "k": [0, 0], "ix": 2 },
              "a": { "a": 0, "k": [0, 0], "ix": 1 },
              "s": { "a": 0, "k": [100, 100], "ix": 3 },
              "r": { "a": 0, "k": 0, "ix": 6 },
              "o": { "a": 0, "k": 100, "ix": 7 },
              "sk": { "a": 0, "k": 0, "ix": 4 },
              "sa": { "a": 0, "k": 0, "ix": 5 },
              "nm": "Transform"
            }
          ],
          "nm": "Group 1",
          "np": 2,
          "cix": 2,
          "bm": 0,
          "ix": 1,
          "mn": "ADBE Vector Group",
          "hd": false
        },
        {
          "ty": "gr",
          "it": [
            {
              "ind": 0,
              "ty": "sh",
              "ix": 1,
              "ks": {
                "a": 0,
                "k": {
                  "i": [
                    [11.66, -11.66],
                    [11.66, 11.66],
                    [-11.66, 11.66],
                    [-11.66, -11.66]
                  ],
                  "o": [
                    [-11.66, 11.66],
                    [-11.66, -11.66],
                    [11.66, -11.66],
                    [11.66, 11.66]
                  ],
                  "v": [
                    [-79.289, 121.513],
                    [-121.513, 121.513],
                    [-121.513, 79.289],
                    [-79.289, 79.289]
                  ],
                  "c": true
                },
                "ix": 2
              },
              "nm": "Path 1",
              "mn": "ADBE Vector Shape - Group",
              "hd": false
            },
            {
              "ty": "st",
              "c": {
                "a": 0,
                "k": [0, 0, 0, 1],
                "ix": 3,
                "x": "var $bm_rt;\n$bm_rt = thisComp.layer('Main Stroke width - Color Ctrl').effect('Base color')('Color');"
              },
              "o": { "a": 0, "k": 100, "ix": 4 },
              "w": {
                "a": 0,
                "k": 16,
                "ix": 5,
                "x": "var $bm_rt;\n$bm_rt = thisComp.layer('Main Stroke width - Color Ctrl').effect('Stroke width')('Slider');"
              },
              "lc": 2,
              "lj": 2,
              "bm": 0,
              "nm": "Stroke 1",
              "mn": "ADBE Vector Graphic - Stroke",
              "hd": false
            },
            {
              "ty": "tr",
              "p": { "a": 0, "k": [0, 0], "ix": 2 },
              "a": { "a": 0, "k": [0, 0], "ix": 1 },
              "s": { "a": 0, "k": [100, 100], "ix": 3 },
              "r": { "a": 0, "k": 0, "ix": 6 },
              "o": { "a": 0, "k": 100, "ix": 7 },
              "sk": { "a": 0, "k": 0, "ix": 4 },
              "sa": { "a": 0, "k": 0, "ix": 5 },
              "nm": "Transform"
            }
          ],
          "nm": "Group 2",
          "np": 2,
          "cix": 2,
          "bm": 0,
          "ix": 2,
          "mn": "ADBE Vector Group",
          "hd": false
        }
      ],
      "ip": 0,
      "op": 50,
      "st": 0,
      "bm": 0
    },
    {
      "ddd": 0,
      "ind": 5,
      "ty": 4,
      "nm": "Main Line",
      "parent": 4,
      "sr": 1,
      "ks": {
        "o": { "a": 0, "k": 100, "ix": 11 },
        "r": { "a": 0, "k": 0, "ix": 10 },
        "p": { "a": 0, "k": [0, 0, 0], "ix": 2 },
        "a": { "a": 0, "k": [0, 0, 0], "ix": 1 },
        "s": { "a": 0, "k": [100, 100, 100], "ix": 6 }
      },
      "ao": 0,
      "shapes": [
        {
          "ty": "gr",
          "it": [
            {
              "ind": 0,
              "ty": "sh",
              "ix": 1,
              "ks": {
                "a": 0,
                "k": {
                  "i": [[0, 0], [0, 0]],
                  "o": [[0, 0], [0, 0]],
                  "v": [[111.928, -111.928], [-79.289, 79.289]],
                  "c": false
                },
                "ix": 2
              },
              "nm": "Path 1",
              "mn": "ADBE Vector Shape - Group",
              "hd": false
            },
            {
              "ty": "st",
              "c": {
                "a": 0,
                "k": [0.20000000298, 0.800000011921, 0.800000011921, 1],
                "ix": 3,
                "x": "var $bm_rt;\n$bm_rt = thisComp.layer('Main Stroke width - Color Ctrl').effect('Highlight')('Color');"
              },
              "o": { "a": 0, "k": 100, "ix": 4 },
              "w": {
                "a": 0,
                "k": 16,
                "ix": 5,
                "x": "var $bm_rt;\n$bm_rt = thisComp.layer('Main Stroke width - Color Ctrl').effect('Stroke width')('Slider');"
              },
              "lc": 2,
              "lj": 2,
              "bm": 0,
              "nm": "Stroke 1",
              "mn": "ADBE Vector Graphic - Stroke",
              "hd": false
            },
            {
              "ty": "tr",
              "p": { "a": 0, "k": [0, 0], "ix": 2 },
              "a": { "a": 0, "k": [0, 0], "ix": 1 },
              "s": { "a": 0, "k": [100, 100], "ix": 3 },
              "r": { "a": 0, "k": 0, "ix": 6 },
              "o": { "a": 0, "k": 100, "ix": 7 },
              "sk": { "a": 0, "k": 0, "ix": 4 },
              "sa": { "a": 0, "k": 0, "ix": 5 },
              "nm": "Transform"
            }
          ],
          "nm": "Group 1",
          "np": 2,
          "cix": 2,
          "bm": 0,
          "ix": 1,
          "mn": "ADBE Vector Group",
          "hd": false
        },
        {
          "ty": "tm",
          "s": {
            "a": 1,
            "k": [
              {
                "i": { "x": [0.53], "y": [1] },
                "o": { "x": [0.47], "y": [0] },
                "t": 0,
                "s": [46]
              },
              {
                "i": { "x": [0.53], "y": [1] },
                "o": { "x": [0.47], "y": [0] },
                "t": 12,
                "s": [0]
              },
              {
                "i": { "x": [0.53], "y": [1] },
                "o": { "x": [0.47], "y": [0] },
                "t": 15,
                "s": [16]
              },
              {
                "i": { "x": [0.53], "y": [1] },
                "o": { "x": [0.47], "y": [0] },
                "t": 21,
                "s": [0]
              },
              { "t": 28, "s": [46] }
            ],
            "ix": 1
          },
          "e": { "a": 0, "k": 100, "ix": 2 },
          "o": { "a": 0, "k": 0, "ix": 3 },
          "m": 1,
          "ix": 2,
          "nm": "Trim Paths 1",
          "mn": "ADBE Vector Filter - Trim",
          "hd": false
        }
      ],
      "ip": 0,
      "op": 50,
      "st": 0,
      "bm": 0
    },
    {
      "ddd": 0,
      "ind": 6,
      "ty": 4,
      "nm": "Lines",
      "parent": 4,
      "sr": 1,
      "ks": {
        "o": { "a": 0, "k": 100, "ix": 11 },
        "r": { "a": 0, "k": 0, "ix": 10 },
        "p": { "a": 0, "k": [0, 0, 0], "ix": 2 },
        "a": { "a": 0, "k": [0, 0, 0], "ix": 1 },
        "s": { "a": 0, "k": [100, 100, 100], "ix": 6 }
      },
      "ao": 0,
      "shapes": [
        {
          "ty": "gr",
          "it": [
            {
              "ind": 0,
              "ty": "sh",
              "ix": 1,
              "ks": {
                "a": 0,
                "k": {
                  "i": [[0, 0], [0, 0]],
                  "o": [[0, 0], [0, 0]],
                  "v": [[27.928, 56.522], [-14.293, 14.3]],
                  "c": false
                },
                "ix": 2
              },
              "nm": "Path 1",
              "mn": "ADBE Vector Shape - Group",
              "hd": false
            },
            {
              "ty": "st",
              "c": {
                "a": 0,
                "k": [0, 0, 0, 1],
                "ix": 3,
                "x": "var $bm_rt;\n$bm_rt = thisComp.layer('Main Stroke width - Color Ctrl').effect('Base color')('Color');"
              },
              "o": { "a": 0, "k": 100, "ix": 4 },
              "w": {
                "a": 0,
                "k": 16,
                "ix": 5,
                "x": "var $bm_rt;\n$bm_rt = thisComp.layer('Main Stroke width - Color Ctrl').effect('Stroke width')('Slider');"
              },
              "lc": 2,
              "lj": 2,
              "bm": 0,
              "nm": "Stroke 1",
              "mn": "ADBE Vector Graphic - Stroke",
              "hd": false
            },
            {
              "ty": "tr",
              "p": { "a": 0, "k": [0, 0], "ix": 2 },
              "a": { "a": 0, "k": [0, 0], "ix": 1 },
              "s": { "a": 0, "k": [100, 100], "ix": 3 },
              "r": { "a": 0, "k": 0, "ix": 6 },
              "o": { "a": 0, "k": 100, "ix": 7 },
              "sk": { "a": 0, "k": 0, "ix": 4 },
              "sa": { "a": 0, "k": 0, "ix": 5 },
              "nm": "Transform"
            }
          ],
          "nm": "Group 1",
          "np": 2,
          "cix": 2,
          "bm": 0,
          "ix": 1,
          "mn": "ADBE Vector Group",
          "hd": false
        },
        {
          "ty": "gr",
          "it": [
            {
              "ind": 0,
              "ty": "sh",
              "ix": 1,
              "ks": {
                "a": 0,
                "k": {
                  "i": [[0, 0], [0, 0]],
                  "o": [[0, 0], [0, 0]],
                  "v": [[70.153, 14.297], [27.932, -27.925]],
                  "c": false
                },
                "ix": 2
              },
              "nm": "Path 1",
              "mn": "ADBE Vector Shape - Group",
              "hd": false
            },
            {
              "ty": "st",
              "c": {
                "a": 0,
                "k": [0, 0, 0, 1],
                "ix": 3,
                "x": "var $bm_rt;\n$bm_rt = thisComp.layer('Main Stroke width - Color Ctrl').effect('Base color')('Color');"
              },
              "o": { "a": 0, "k": 100, "ix": 4 },
              "w": {
                "a": 0,
                "k": 16,
                "ix": 5,
                "x": "var $bm_rt;\n$bm_rt = thisComp.layer('Main Stroke width - Color Ctrl').effect('Stroke width')('Slider');"
              },
              "lc": 2,
              "lj": 2,
              "bm": 0,
              "nm": "Stroke 1",
              "mn": "ADBE Vector Graphic - Stroke",
              "hd": false
            },
            {
              "ty": "tr",
              "p": { "a": 0, "k": [0, 0], "ix": 2 },
              "a": { "a": 0, "k": [0, 0], "ix": 1 },
              "s": { "a": 0, "k": [100, 100], "ix": 3 },
              "r": { "a": 0, "k": 0, "ix": 6 },
              "o": { "a": 0, "k": 100, "ix": 7 },
              "sk": { "a": 0, "k": 0, "ix": 4 },
              "sa": { "a": 0, "k": 0, "ix": 5 },
              "nm": "Transform"
            }
          ],
          "nm": "Group 2",
          "np": 2,
          "cix": 2,
          "bm": 0,
          "ix": 2,
          "mn": "ADBE Vector Group",
          "hd": false
        },
        {
          "ty": "gr",
          "it": [
            {
              "ind": 0,
              "ty": "sh",
              "ix": 1,
              "ks": {
                "a": 0,
                "k": {
                  "i": [[0, 0], [0, 0]],
                  "o": [[0, 0], [0, 0]],
                  "v": [[112.378, -27.928], [70.157, -70.149]],
                  "c": false
                },
                "ix": 2
              },
              "nm": "Path 1",
              "mn": "ADBE Vector Shape - Group",
              "hd": false
            },
            {
              "ty": "st",
              "c": {
                "a": 0,
                "k": [0, 0, 0, 1],
                "ix": 3,
                "x": "var $bm_rt;\n$bm_rt = thisComp.layer('Main Stroke width - Color Ctrl').effect('Base color')('Color');"
              },
              "o": { "a": 0, "k": 100, "ix": 4 },
              "w": {
                "a": 0,
                "k": 16,
                "ix": 5,
                "x": "var $bm_rt;\n$bm_rt = thisComp.layer('Main Stroke width - Color Ctrl').effect('Stroke width')('Slider');"
              },
              "lc": 2,
              "lj": 2,
              "bm": 0,
              "nm": "Stroke 1",
              "mn": "ADBE Vector Graphic - Stroke",
              "hd": false
            },
            {
              "ty": "tr",
              "p": { "a": 0, "k": [0, 0], "ix": 2 },
              "a": { "a": 0, "k": [0, 0], "ix": 1 },
              "s": { "a": 0, "k": [100, 100], "ix": 3 },
              "r": { "a": 0, "k": 0, "ix": 6 },
              "o": { "a": 0, "k": 100, "ix": 7 },
              "sk": { "a": 0, "k": 0, "ix": 4 },
              "sa": { "a": 0, "k": 0, "ix": 5 },
              "nm": "Transform"
            }
          ],
          "nm": "Group 3",
          "np": 2,
          "cix": 2,
          "bm": 0,
          "ix": 3,
          "mn": "ADBE Vector Group",
          "hd": false
        },
        {
          "ty": "gr",
          "it": [
            {
              "ind": 0,
              "ty": "sh",
              "ix": 1,
              "ks": {
                "a": 0,
                "k": {
                  "i": [[0, 0], [0, 0]],
                  "o": [[0, 0], [0, 0]],
                  "v": [[154.603, -70.153], [112.381, -112.374]],
                  "c": false
                },
                "ix": 2
              },
              "nm": "Path 1",
              "mn": "ADBE Vector Shape - Group",
              "hd": false
            },
            {
              "ty": "st",
              "c": {
                "a": 0,
                "k": [0, 0, 0, 1],
                "ix": 3,
                "x": "var $bm_rt;\n$bm_rt = thisComp.layer('Main Stroke width - Color Ctrl').effect('Base color')('Color');"
              },
              "o": { "a": 0, "k": 100, "ix": 4 },
              "w": {
                "a": 0,
                "k": 16,
                "ix": 5,
                "x": "var $bm_rt;\n$bm_rt = thisComp.layer('Main Stroke width - Color Ctrl').effect('Stroke width')('Slider');"
              },
              "lc": 2,
              "lj": 2,
              "bm": 0,
              "nm": "Stroke 1",
              "mn": "ADBE Vector Graphic - Stroke",
              "hd": false
            },
            {
              "ty": "tr",
              "p": { "a": 0, "k": [0, 0], "ix": 2 },
              "a": { "a": 0, "k": [0, 0], "ix": 1 },
              "s": { "a": 0, "k": [100, 100], "ix": 3 },
              "r": { "a": 0, "k": 0, "ix": 6 },
              "o": { "a": 0, "k": 100, "ix": 7 },
              "sk": { "a": 0, "k": 0, "ix": 4 },
              "sa": { "a": 0, "k": 0, "ix": 5 },
              "nm": "Transform"
            }
          ],
          "nm": "Group 4",
          "np": 2,
          "cix": 2,
          "bm": 0,
          "ix": 4,
          "mn": "ADBE Vector Group",
          "hd": false
        }
      ],
      "ip": 0,
      "op": 50,
      "st": 0,
      "bm": 0
    },
    {
      "ddd": 0,
      "ind": 7,
      "ty": 4,
      "nm": "Color",
      "parent": 4,
      "sr": 1,
      "ks": {
        "o": { "a": 0, "k": 100, "ix": 11 },
        "r": { "a": 0, "k": 0, "ix": 10 },
        "p": { "a": 0, "k": [0.18, 1.532, 0], "ix": 2 },
        "a": { "a": 0, "k": [203.724, 205.012, 0], "ix": 1 },
        "s": { "a": 0, "k": [96, 96, 100], "ix": 6 }
      },
      "ao": 0,
      "shapes": [
        {
          "ty": "gr",
          "it": [
            {
              "ind": 0,
              "ty": "sh",
              "ix": 1,
              "ks": {
                "a": 0,
                "k": {
                  "i": [
                    [11.958, -11.958],
                    [11.958, 11.958],
                    [-11.958, 11.958],
                    [-11.958, -11.958]
                  ],
                  "o": [
                    [-11.958, 11.958],
                    [-11.958, -11.958],
                    [11.958, -11.958],
                    [11.958, 11.958]
                  ],
                  "v": [
                    [21.652, 21.652],
                    [-21.652, 21.652],
                    [-21.652, -21.652],
                    [21.652, -21.652]
                  ],
                  "c": true
                },
                "ix": 2
              },
              "nm": "Path 1",
              "mn": "ADBE Vector Shape - Group",
              "hd": false
            },
            {
              "ty": "fl",
              "c": {
                "a": 0,
                "k": [0.992156922583, 0.376470618154, 0.313725490196, 1],
                "ix": 4
              },
              "o": { "a": 0, "k": 100, "ix": 5 },
              "r": 1,
              "bm": 0,
              "nm": "Fill 1",
              "mn": "ADBE Vector Graphic - Fill",
              "hd": false
            },
            {
              "ty": "tr",
              "p": { "a": 0, "k": [101.081, 308.943], "ix": 2 },
              "a": { "a": 0, "k": [0, 0], "ix": 1 },
              "s": { "a": 0, "k": [100, 100], "ix": 3 },
              "r": { "a": 0, "k": 0, "ix": 6 },
              "o": { "a": 0, "k": 100, "ix": 7 },
              "sk": { "a": 0, "k": 0, "ix": 4 },
              "sa": { "a": 0, "k": 0, "ix": 5 },
              "nm": "Transform"
            }
          ],
          "nm": "Group 1",
          "np": 2,
          "cix": 2,
          "bm": 0,
          "ix": 1,
          "mn": "ADBE Vector Group",
          "hd": false
        },
        {
          "ty": "gr",
          "it": [
            {
              "ind": 0,
              "ty": "sh",
              "ix": 1,
              "ks": {
                "a": 0,
                "k": {
                  "i": [
                    [0, 0],
                    [19.24, -19.24],
                    [35.88, 35.872],
                    [-35.872, 35.872],
                    [-25.184, -1.392],
                    [0, 0],
                    [-29.088, -29.088],
                    [-10.456, -3.192]
                  ],
                  "o": [
                    [1.392, 25.184],
                    [-35.872, 35.872],
                    [-35.872, -35.88],
                    [19.24, -19.24],
                    [0, 0],
                    [-30.68, 52.464],
                    [7.552, 7.552],
                    [0, 0]
                  ],
                  "v": [
                    [92.38, 26.756],
                    [65.62, 96.82],
                    [-64.292, 96.82],
                    [-64.292, -33.092],
                    [5.772, -59.852],
                    [78.612, -132.692],
                    [72.924, 2.916],
                    [100.164, 18.972]
                  ],
                  "c": true
                },
                "ix": 2
              },
              "nm": "Path 1",
              "mn": "ADBE Vector Shape - Group",
              "hd": false
            },
            {
              "ty": "fl",
              "c": {
                "a": 0,
                "k": [0.992156922583, 0.878431432387, 0.745098039216, 1],
                "ix": 4
              },
              "o": { "a": 0, "k": 100, "ix": 5 },
              "r": 1,
              "bm": 0,
              "nm": "Fill 1",
              "mn": "ADBE Vector Graphic - Fill",
              "hd": false
            },
            {
              "ty": "tr",
              "p": { "a": 0, "k": [100.415, 277.081], "ix": 2 },
              "a": { "a": 0, "k": [0, 0], "ix": 1 },
              "s": { "a": 0, "k": [100, 100], "ix": 3 },
              "r": { "a": 0, "k": 0, "ix": 6 },
              "o": { "a": 0, "k": 100, "ix": 7 },
              "sk": { "a": 0, "k": 0, "ix": 4 },
              "sa": { "a": 0, "k": 0, "ix": 5 },
              "nm": "Transform"
            }
          ],
          "nm": "Group 2",
          "np": 2,
          "cix": 2,
          "bm": 0,
          "ix": 2,
          "mn": "ADBE Vector Group",
          "hd": false
        },
        {
          "ty": "gr",
          "it": [
            {
              "ind": 0,
              "ty": "sh",
              "ix": 1,
              "ks": {
                "a": 0,
                "k": {
                  "i": [
                    [1.394, 25.181],
                    [0, 0],
                    [23.917, 23.916],
                    [23.916, -23.916],
                    [0, 0],
                    [19.237, -19.236],
                    [-35.874, -35.874],
                    [-35.874, 35.875]
                  ],
                  "o": [
                    [0, 0],
                    [23.917, -23.917],
                    [-23.916, -23.916],
                    [0, 0],
                    [-25.182, -1.394],
                    [-35.874, 35.875],
                    [35.875, 35.875],
                    [19.237, -19.237]
                  ],
                  "v": [
                    [-10.928, 97.536],
                    [179.557, -92.949],
                    [179.557, -179.558],
                    [92.949, -179.558],
                    [-97.536, 10.928],
                    [-167.6, 37.686],
                    [-167.6, 167.599],
                    [-37.687, 167.599]
                  ],
                  "c": true
                },
                "ix": 2
              },
              "nm": "Path 1",
              "mn": "ADBE Vector Shape - Group",
              "hd": false
            },
            {
              "ty": "fl",
              "c": { "a": 0, "k": [1, 1, 1, 1], "ix": 4 },
              "o": { "a": 0, "k": 100, "ix": 5 },
              "r": 1,
              "bm": 0,
              "nm": "Fill 1",
              "mn": "ADBE Vector Graphic - Fill",
              "hd": false
            },
            {
              "ty": "tr",
              "p": { "a": 0, "k": [203.724, 203.724], "ix": 2 },
              "a": { "a": 0, "k": [0, 0], "ix": 1 },
              "s": { "a": 0, "k": [100, 100], "ix": 3 },
              "r": { "a": 0, "k": 0, "ix": 6 },
              "o": { "a": 0, "k": 100, "ix": 7 },
              "sk": { "a": 0, "k": 0, "ix": 4 },
              "sa": { "a": 0, "k": 0, "ix": 5 },
              "nm": "Transform"
            }
          ],
          "nm": "Group 3",
          "np": 2,
          "cix": 2,
          "bm": 0,
          "ix": 3,
          "mn": "ADBE Vector Group",
          "hd": false
        }
      ],
      "ip": 0,
      "op": 814.147480814147,
      "st": 0,
      "bm": 0
    },
    {
      "ddd": 0,
      "ind": 8,
      "ty": 3,
      "nm": "Zero | troke width - Color Ctrl",
      "sr": 1,
      "ks": {
        "o": { "a": 0, "k": 0, "ix": 11 },
        "r": { "a": 0, "k": 0, "ix": 10 },
        "p": { "a": 0, "k": [250, 250, 0], "ix": 2 },
        "a": { "a": 0, "k": [0, 0, 0], "ix": 1 },
        "s": { "a": 0, "k": [100, 100, 100], "ix": 6 }
      },
      "ao": 0,
      "ip": 0,
      "op": 50,
      "st": 0,
      "bm": 0
    }
  ],
  "markers": []
}
